tmgen/__init__.pxd
tmgen/__init__.py
tmgen/exceptions.py
tmgen/hmc.cpython-36m-darwin.so
tmgen/hmc.pxd
tmgen/models.cpython-36m-darwin.so
tmgen/models.pxd
tmgen/plot.py
tmgen/tm.cpython-36m-darwin.so
tmgen/tm.pxd
tmgen/inject/__init__.py
tmgen/inject/ditg_injector.py
tmgen-0.1.2.dist-info/DESCRIPTION.rst
tmgen-0.1.2.dist-info/METADATA
tmgen-0.1.2.dist-info/RECORD
tmgen-0.1.2.dist-info/WHEEL
tmgen-0.1.2.dist-info/entry_points.txt
tmgen-0.1.2.dist-info/metadata.json
tmgen-0.1.2.dist-info/top_level.txt
