Metadata-Version: 2.0
Name: tmgen
Version: 0.1.2
Summary: Library for network traffic matrix generation
Home-page: https://github.com/progwriter/TMgen
Author: Victor Heorhiadi
Author-email: victor@cs.unc.edu
License: MIT
Keywords: network,traffic,matrix
Platform: UNKNOWN
Classifier: Development Status :: 3 - Alpha
Classifier: Intended Audience :: Science/Research
Classifier: License :: OSI Approved :: MIT License
Classifier: Programming Language :: Python :: 2
Classifier: Programming Language :: Python :: 2.7
Classifier: Programming Language :: Python :: 3
Classifier: Programming Language :: Python :: 3.4
Classifier: Programming Language :: Python :: 3.5
Classifier: Programming Language :: Python :: 3.6
Classifier: Topic :: System :: Networking
Classifier: Topic :: Software Development :: Libraries :: Python Modules
Requires-Dist: numpy
Requires-Dist: cython
Requires-Dist: six
Provides-Extra: plotting
Requires-Dist: matplotlib; extra == 'plotting'
Requires-Dist: seaborn; extra == 'plotting'
